pytest_picked/__init__.py
pytest_picked/modes.py
pytest_picked/plugin.py
pytest_picked-0.5.1.dist-info/LICENSE
pytest_picked-0.5.1.dist-info/METADATA
pytest_picked-0.5.1.dist-info/WHEEL
pytest_picked-0.5.1.dist-info/entry_points.txt
pytest_picked-0.5.1.dist-info/top_level.txt
pytest_picked-0.5.1.dist-info/RECORD
