Metadata-Version: 2.1
Name: pytest-picked
Version: 0.5.1
Summary: Run the tests related to the changed files
Author-email: Ana Paula Gomes <apgomes88@gmail.com>
License: MIT
Keywords: pytest,testing,changed files,selective tests
Classifier: Framework :: Pytest
Classifier: Intended Audience :: Developers
Classifier: Topic :: Software Development :: Testing
Classifier: Programming Language :: Python
Classifier: Programming Language :: Python :: 3.8
Classifier: Programming Language :: Python :: 3.9
Classifier: Programming Language :: Python :: 3.10
Classifier: Programming Language :: Python :: 3.11
Classifier: License :: OSI Approved :: MIT License
Requires-Python: >=3.8
License-File: LICENSE
Requires-Dist: pytest >=3.7.0
